{
    "title": "Determine and document the support period",
    "cardType": "base/cardTypes/annualTask",
    "workflowState": "Open",
    "rank": "0|zp",
    "base/fieldTypes/owner": null,
    "base/fieldTypes/informationClassification": "internal",
    "base/fieldTypes/reviewPeriod": 360,
    "base/fieldTypes/justification": null,
    "base/fieldTypes/reviewMonth": null,
    "base/fieldTypes/lastReviewed": null,
    "base/fieldTypes/adoptionStep": "step1",
    "base/fieldTypes/identifier": "eucra_control_support-period",
    "links": [],
    "lastUpdated": "2025-09-16T17:35:33.052Z",
    "templateCardKey": "eucra_kug80ook"
}